{"name":"Sonarqube-puppet","tagline":"Sonarqube 4.1.1 Puppet install with Vagrant","body":"# Sonarqube puppet installation\r\n\r\nInstall Sonarqube 4.1.1 using Puppet in a Virtual Machine with Vagrant\r\n\r\n## Requirements\r\n\r\n* [Download Vagrant](https://www.vagrantup.com/downloads)\r\n* Enable virtualization\r\n\r\n## Run\r\n\r\nExecute vagrant:\r\n\r\n```shell\r\n$ vagrant up\r\n```\r\n\r\n## License\r\n\r\n## GPLv3 License\r\n\r\nThis application is published by [GPLv3](http://www.gnu.org/licenses/gpl.html)\r\n\r\n## Document License\r\n\r\n<a href=\"http://creativecommons.org/licenses/by/3.0/\" rel=\"Creative Commons Attribution 3.0\">![Foo](http://i.creativecommons.org/l/by/3.0/88x31.png)</a>\r\n\r\nThis work by Ricardo Gracía Fernández - ricardogarfe [at] gmail [dot] com is licensed under a [Creative Commons Attribution 3.0 Unported License](http://creativecommons.org/licenses/by/3.0/).\r\n\r\n","google":"","note":"Don't delete this file! It's used internally to help with page regeneration."}